README.md
setup.py
tully/__init__.py
tully/__main__.py
tully/cli.py
tully/covid19.py
tully/network.py
tully.egg-info/PKG-INFO
tully.egg-info/SOURCES.txt
tully.egg-info/dependency_links.txt
tully.egg-info/entry_points.txt
tully.egg-info/requires.txt
tully.egg-info/top_level.txt