Metadata-Version: 1.1
Name: tully
Version: 0.2.0
Summary: A collection of useful commands to use at the command line.
Home-page: https://github.com/tullyrankin/tully
Author: Tully Rankin
Author-email: tully.rankin@gmail.com
License: UNKNOWN
Platform: UNKNOWN
Classifier: Programming Language :: Python :: 3
Classifier: License :: OSI Approved :: MIT License
Classifier: Operating System :: OS Independent
